ukchurn_classification_model/__init__.py
ukchurn_classification_model/pipeline.py
ukchurn_classification_model/predict.py
ukchurn_classification_model/train_pipeline.py
ukchurn_classification_model/config/__init__.py
ukchurn_classification_model/config/config.py
ukchurn_classification_model/data_management/__init__.py
ukchurn_classification_model/data_management/data_validation.py
ukchurn_classification_model/data_management/pipeline_management.py
ukchurn_classification_model/preprocessors/__init__.py
ukchurn_classification_model/preprocessors/categorical_encoder.py
ukchurn_classification_model/preprocessors/categorical_imputer.py
ukchurn_classification_model/preprocessors/numerical_imputer.py
ukchurn_classification_model/tests/__init__.py
ukchurn_classification_model/tests/integration_tests/__init__.py
ukchurn_classification_model/tests/model_quality_tests/__init__.py
ukchurn_classification_model/tests/unit_tests/__init__.py
ukchurn_classification_model/tests/unit_tests/test_predict.py
ukchurn_classification_model/trained_model/uk_churn_model.pkl
ukchurn_classification_model-0.2.dist-info/METADATA
ukchurn_classification_model-0.2.dist-info/WHEEL
ukchurn_classification_model-0.2.dist-info/top_level.txt
ukchurn_classification_model-0.2.dist-info/RECORD
