Metadata-Version: 2.1
Name: ukchurn-classification-model
Version: 0.2
Summary: A library for predicting pannelist churn.
Home-page: https://github.com/diogo22santos/churn_model.git
Author: Lisbon Data Science Hub
Author-email: diogo.santos@kantar.com
License: MIT
Platform: UNKNOWN
Requires-Python: >=3.7.4
Requires-Dist: atomicwrites (==1.3.0)
Requires-Dist: attrs (==19.1.0)
Requires-Dist: bleach (==3.1.0)
Requires-Dist: certifi (==2019.6.16)
Requires-Dist: chardet (==3.0.4)
Requires-Dist: colorama (==0.4.1)
Requires-Dist: docutils (==0.15.2)
Requires-Dist: idna (==2.8)
Requires-Dist: importlib-metadata (==0.20)
Requires-Dist: joblib (==0.13.2)
Requires-Dist: more-itertools (==7.2.0)
Requires-Dist: nose (==1.3.7)
Requires-Dist: numpy (==1.17.1)
Requires-Dist: packaging (==19.1)
Requires-Dist: pandas (==0.25.1)
Requires-Dist: pkginfo (==1.5.0.1)
Requires-Dist: pluggy (==0.12.0)
Requires-Dist: py (==1.8.0)
Requires-Dist: Pygments (==2.4.2)
Requires-Dist: pyparsing (==2.4.2)
Requires-Dist: pytest (==5.1.2)
Requires-Dist: python-dateutil (==2.8.0)
Requires-Dist: pytz (==2019.2)
Requires-Dist: readme-renderer (==24.0)
Requires-Dist: requests (==2.22.0)
Requires-Dist: requests-toolbelt (==0.9.1)
Requires-Dist: scikit-learn (==0.21.3)
Requires-Dist: scipy (==1.3.1)
Requires-Dist: six (==1.12.0)
Requires-Dist: sklearn (==0.0)
Requires-Dist: tqdm (==4.35.0)
Requires-Dist: twine (==1.13.0)
Requires-Dist: urllib3 (==1.25.3)
Requires-Dist: wcwidth (==0.1.7)
Requires-Dist: webencodings (==0.5.1)
Requires-Dist: wincertstore (==0.2)
Requires-Dist: xgboost (==0.90)
Requires-Dist: zipp (==0.6.0)
